{
  "main": {
    "id": "22615b0bbde792d5",
    "type": "split",
    "children": [
      {
        "id": "abc02b802ed6ad62",
        "type": "tabs",
        "children": [
          {
            "id": "46a69b46a9fad369",
            "type": "leaf",
            "state": {
              "type": "markdown",
              "state": {
                "file": "Leertraject/2025-W45.md",
                "mode": "source",
                "source": true
              },
              "icon": "lucide-file",
              "title": "2025-W45"
            }
          }
        ]
      }
    ],
    "direction": "vertical"
  },
  "left": {
    "id": "e09bac64b058d4b4",
    "type": "split",
    "children": [
      {
        "id": "0320eed3fa6928bf",
        "type": "tabs",
        "children": [
          {
            "id": "92d32d5199956397",
            "type": "leaf",
            "state": {
              "type": "file-explorer",
              "state": {
                "sortOrder": "alphabetical",
                "autoReveal": false
              },
              "icon": "lucide-folder-closed",
              "title": "Files"
            }
          },
          {
            "id": "d720ba9a87817982",
            "type": "leaf",
            "state": {
              "type": "search",
              "state": {
                "query": "",
                "matchingCase": false,
                "explainSearch": false,
                "collapseAll": false,
                "extraContext": false,
                "sortOrder": "alphabetical"
              },
              "icon": "lucide-search",
              "title": "Search"
            }
          },
          {
            "id": "8dbb6ed7f6401e49",
            "type": "leaf",
            "state": {
              "type": "bookmarks",
              "state": {},
              "icon": "lucide-bookmark",
              "title": "Bookmarks"
            }
          }
        ]
      }
    ],
    "direction": "horizontal",
    "width": 452.5
  },
  "right": {
    "id": "5e1f4ee143262312",
    "type": "split",
    "children": [
      {
        "id": "eb187976d6128f87",
        "type": "tabs",
        "children": [
          {
            "id": "0ebae8d7fcace7c0",
            "type": "leaf",
            "state": {
              "type": "backlink",
              "state": {
                "collapseAll": false,
                "extraContext": false,
                "sortOrder": "alphabetical",
                "showSearch": false,
                "searchQuery": "",
                "backlinkCollapsed": false,
                "unlinkedCollapsed": true
              },
              "icon": "links-coming-in",
              "title": "Backlinks"
            }
          },
          {
            "id": "e4dd2ead417a344e",
            "type": "leaf",
            "state": {
              "type": "outgoing-link",
              "state": {
                "file": "Welcome.md",
                "linksCollapsed": false,
                "unlinkedCollapsed": true
              },
              "icon": "links-going-out",
              "title": "Outgoing links from Welcome"
            }
          },
          {
            "id": "a99b600e11f11493",
            "type": "leaf",
            "state": {
              "type": "tag",
              "state": {
                "sortOrder": "frequency",
                "useHierarchy": true,
                "showSearch": false,
                "searchQuery": ""
              },
              "icon": "lucide-tags",
              "title": "Tags"
            }
          },
          {
            "id": "7cd70e6b75460811",
            "type": "leaf",
            "state": {
              "type": "outline",
              "state": {
                "file": "Leertraject/2025-W45.md",
                "followCursor": false,
                "showSearch": false,
                "searchQuery": ""
              },
              "icon": "lucide-list",
              "title": "Outline of 2025-W45"
            }
          }
        ],
        "currentTab": 3
      }
    ],
    "direction": "horizontal",
    "width": 200
  },
  "left-ribbon": {
    "hiddenItems": {
      "switcher:Open quick switcher": false,
      "graph:Open graph view": false,
      "canvas:Create new canvas": false,
      "daily-notes:Open today's daily note": false,
      "templates:Insert template": false,
      "command-palette:Open command palette": false,
      "bases:Create new base": false,
      "templater-obsidian:Templater": false
    }
  },
  "active": "46a69b46a9fad369",
  "lastOpenFiles": [
    "SEM01/SEM01 Orientatie Keuze.md",
    "Untitled.md",
    "SEM01/Diagram/ER Diagram.md",
    "SEM01/Workshops/Workshop Infrastructure.md",
    "SEM01/Diagram/Powerlifting PC Flow chart.md",
    "Leertraject/2025-W45.md",
    "SEM01/Vragen.md",
    "SEM01/Diagram/Powerlifting Database diagram.md",
    "SEM01/Diagram/Powerlifting Chen Notatie.md",
    "SEM01/Diagram/Powerlifting Class diagram.md",
    "Leertraject/2025-W44.md",
    "SEM01/Diagram/Powerlifting Database diagram Learned.md",
    "Templates/Leertraject - Weekkaart.md",
    "Leertraject/2025-W46.md",
    "Werk/DB Wegen.md",
    "Werk/DB Groen.md",
    "2025-11-02.md",
    "Templates/Leertraject - Weekkaart 1.md",
    "Leertraject/2025-W46.md",
    "Leertraject/2025-W43.md",
    "SEM01/Reflectie UX-design.md",
    "SEM01/Diagram/Powerlifting Arduino State Diagram.md",
    "SEM01/Eindproduct/Design v2.md",
    "SEM01/Eindproduct",
    "Canvas/Leertraject-tijdlijn.canvas",
    "SEM01/Diagram",
    "SEM01/Reflectie project Sem01.md",
    "SEM01/Oriëntatie Sem 01.md",
    "SEM01/Lessen Arduino probeersels.md",
    "Werk/DB Wegen",
    "Werk",
    "Untitled.canvas",
    "SEM01",
    "Excalidraw",
    "Canvas",
    "Templates",
    "Leertraject",
    "SEM01/Leerdoelen/Leerdoelen per topic",
    "20250924_Leerdoelen.png",
    "Pasted image 20250924140631.png"
  ]
}